{
    "board1": {
        "groundOffset": 180,
        "hasSpectators": false,
        "hasSideLineSpectators": false,
        "teacherOffset": {"x": 220, "y": -100},
        "useTimer": true,
        "timerOffset":  {"x": 0, "y": 0},
        "isBreakingBoard": false,
        "isTrainingBoard": false
    },
    "board2": {
        "groundOffset": 210,
        "hasSpectators": false,
        "hasSideLineSpectators": false,
        "teacherOffset": {"x": 0, "y": 0},
        "useTimer": true,
        "timerOffset":  {"x": 1, "y": -2},
        "isBreakingBoard": true,
        "isTrainingBoard": true
    },
    "board3": {
        "groundOffset": 170,
        "hasSpectators": false,
        "hasSideLineSpectators": false,
        "teacherOffset": {"x": 0, "y": 0},
        "useTimer": true,
        "timerOffset":  {"x": 0, "y": -8},
        "isBreakingBoard": true,
        "isTrainingBoard": true
    },
    "board4": {
        "groundOffset": 120,
        "hasSpectators": false,
        "hasSideLineSpectators": false,
        "teacherOffset": {"x": 0, "y": 0},
        "useTimer": true,
        "timerOffset":  {"x": 0, "y": -5},
        "isBreakingBoard": true
    },
    "board5": {
        "groundOffset": 100,
        "hasSpectators": false,
        "hasSideLineSpectators": false,
        "teacherOffset": {"x": 0, "y": 0},
        "useTimer": true,
        "timerOffset":  {"x": 0, "y": -5},
        "isBreakingBoard": true,
        "isTrainingBoard": true
    },
    "board6": {
        "groundOffset": 200,
        "hasSpectators": true,
        "hasSideLineSpectators": true,
        "teacherOffset": {"x": 0, "y": -130},
        "useTimer": true,
        "timerOffset":  {"x": 0, "y": -55},
        "isBreakingBoard": false,
        "isTrainingBoard": true
    },
    "board7": {
        "groundOffset": 200,
        "hasSpectators": false,
        "hasSideLineSpectators": false,
        "teacherOffset": {"x": 0, "y": 0},
        "useTimer": true,
        "timerOffset":  {"x": -250, "y": 100},
        "isBreakingBoard": false,
        "isTrainingBoard": true
    }
}